src/__init__.py
src/data_manager.py
src/dictionary_manager.py
src/gui.py
src/utils.py
dictionary_app-1.0.1.dist-info/METADATA
dictionary_app-1.0.1.dist-info/WHEEL
dictionary_app-1.0.1.dist-info/entry_points.txt
dictionary_app-1.0.1.dist-info/top_level.txt
dictionary_app-1.0.1.dist-info/RECORD
