Metadata-Version: 2.2
Name: dictionary-app
Version: 1.0.1
Summary: A simple desktop application for managing a personal dictionary of terms and definitions.
Home-page: https://github.com/keithwalsh/dictionary-app
Author: Keith Walsh
Author-email: keithwalsh@gmail.com
Classifier: Development Status :: 5 - Production/Stable
Classifier: Intended Audience :: End Users/Desktop
Classifier: License :: OSI Approved :: MIT License
Classifier: Programming Language :: Python :: 3.9
Classifier: Programming Language :: Python :: 3.10
Classifier: Programming Language :: Python :: 3.11
Classifier: Topic :: Office/Business
Requires-Python: >=3.9
Dynamic: author
Dynamic: author-email
Dynamic: classifier
Dynamic: description
Dynamic: description-content-type
Dynamic: home-page
Dynamic: requires-python
Dynamic: summary
